MANIFEST.in
README.md
setup.py
spswarehouse/__init__.py
spswarehouse/credentials.py.template
spswarehouse/googlesheets.py
spswarehouse/requirements.txt
spswarehouse/table_names.py
spswarehouse/table_utils.py
spswarehouse/warehouse.py
spswarehouse_hs_test.egg-info/PKG-INFO
spswarehouse_hs_test.egg-info/SOURCES.txt
spswarehouse_hs_test.egg-info/dependency_links.txt
spswarehouse_hs_test.egg-info/top_level.txt