Metadata-Version: 2.1
Name: spswarehouse-hs-test
Version: 0.0.3
Summary: Summit Public Schools Snowflake warehouse
Home-page: https://github.com/SummitPublicSchools/spswarehouse
Author: Harry Li Consulting, LLC
Author-email: hcli.consulting@gmail.com
License: UNKNOWN
Platform: UNKNOWN
Classifier: Programming Language :: Python :: 3
